astunparse/__init__.py
astunparse/__main__.py
astunparse/printer.py
astunparse/unparser.py
astunparse_fixed-1.7.0.dist-info/AUTHORS.rst
astunparse_fixed-1.7.0.dist-info/LICENSE
astunparse_fixed-1.7.0.dist-info/METADATA
astunparse_fixed-1.7.0.dist-info/WHEEL
astunparse_fixed-1.7.0.dist-info/top_level.txt
astunparse_fixed-1.7.0.dist-info/RECORD
