Metadata-Version: 2.1
Name: astunparse-fixed
Version: 1.7.0
Summary: An AST unparser for Python
Home-page: https://github.com/simonpercivall/astunparse
Maintainer: Simon Percivall
Maintainer-email: percivall@gmail.com
License: BSD
Keywords: astunparse
Classifier: Development Status :: 5 - Production/Stable
Classifier: Intended Audience :: Developers
Classifier: License :: OSI Approved :: BSD License
Classifier: Natural Language :: English
Classifier: Programming Language :: Python :: 2
Classifier: Programming Language :: Python :: 2.7
Classifier: Programming Language :: Python :: 3
Classifier: Programming Language :: Python :: 3.5
Classifier: Programming Language :: Python :: 3.6
Classifier: Programming Language :: Python :: 3.7
Classifier: Programming Language :: Python :: 3.8
Classifier: Topic :: Software Development :: Code Generators
License-File: LICENSE
License-File: AUTHORS.rst
Requires-Dist: wheel (<1.0,>=0.23.0)
Requires-Dist: six (<2.0,>=1.6.1)
